<?xml version="1.0" encoding="UTF-8"?>
<!DOCTYPE hibernate-mapping PUBLIC "-//Hibernate/Hibernate Mapping DTD 3.0//EN" "http://hibernate.sourceforge.net/hibernate-mapping-3.0.dtd">

<hibernate-mapping
	package="gov.nih.nci.calab.domain.nano.characterization.physical.composition">
	<class name="ComposingElementType"
		table="def_composing_element_type" lazy="true"
		polymorphism="explicit">
		<cache usage="read-write" />
		<id name="id" type="java.lang.Long"
			column="composing_element_type_pk_id" unsaved-value="0">
			<generator class="org.hibernate.id.TableHiLoGenerator">
				<param name="table">hibernate_unique_key</param>
				<param name="column">next_hi</param>
			</generator>
		</id>
		<property name="name" type="java.lang.String" column="name" />
	</class>
	<class name="MolecularFormulaType"
		table="def_molecular_formula_type" lazy="true"
		polymorphism="explicit">
		<cache usage="read-write" />
		<id name="id" type="java.lang.Long"
			column="molecular_formula_type_pk_id" unsaved-value="0">
			<generator class="org.hibernate.id.TableHiLoGenerator">
				<param name="table">hibernate_unique_key</param>
				<param name="column">next_hi</param>
			</generator>
		</id>
		<property name="name" type="java.lang.String" column="name" />
	</class>
	<class name="SurfaceGroupType" table="def_surface_group_type"
		lazy="true" polymorphism="explicit">
		<cache usage="read-write" />
		<id name="id" type="java.lang.Long"
			column="surface_group_type_pk_id" unsaved-value="0">
			<generator class="org.hibernate.id.TableHiLoGenerator">
				<param name="table">hibernate_unique_key</param>
				<param name="column">next_hi</param>
			</generator>
		</id>
		<property name="name" type="java.lang.String" column="name" />
	</class>
</hibernate-mapping>
